{
  "scheme": 1,
  "version": "2024-12-15 14:05 +0800",
  "android": {
    "securityPatchLevel": "2024-12-05",
    "googlePlaySystemUpdates": "2024-12-01",
    "build": {
      "version": "2024-12-10",
      "details": [
        {
          "id": "AP4A.241205.013",
          "revision": "r6"
        },
        {
          "id": "AP4A.241205.013.A2",
          "revision": "r7"
        },
        {
          "id": "AP4A.241205.013.B1",
          "revision": "r8"
        },
        {
          "id": "AP4A.241205.013.C1",
          "revision": "r9"
        }
      ]
    },
    "stable": {
      "name": "VanillaIceCream",
      "api": "35",
      "version": "15, VanillaIceCream"
    },
    "stablePreview": {
      "name": "VanillaIceCream",
      "api": "35",
      "version": "15 QPR2 Beta 1, VanillaIceCream"
    },
    "support": {
      "name": "SnowCone",
      "api": "31",
      "version": "12, SnowCone"
    },
    "preview": {
      "name": "Baklava",
      "api": "36",
      "version": "16 DP1, Baklava",
      "phase": ""
    },
    "internal": {
      "name": "Baklava",
      "api": "36",
      "version": "16 DP1, Baklava"
    }
  },
  "linux": {
    "google": {
      "versions": [
        "6.6.66",
        "6.1.120",
        "5.15.174",
        "5.10.231",
        "5.4.287",
        "4.19.325"
      ]
    },
    "mainline": {
      "version": "6.13-rc2"
    }
  },
  "toybox": {
    "stable": {
      "version": "0.8.11"
    },
    "support": {
      "version": "0.8.4"
    },
    "mainline": {
      "version": "0.8.11"
    },
    "master": {
      "version": "0.8.11"
    }
  },
  "webView": {
    "stable": {
      "version": "131.0.6778.135"
    },
    "beta": {
      "version": "132.0.6834.43"
    }
  }
}
